{
  "version": "2.0.2",
  "mobileAppVersion": "2.0.2",
  "releaseNotes": "* '@shoutem/ui' package version bugfix",
  "settings": {
    "DEV-appetizeKey": "90dycv9gb098u6xytcb6jnkvw8",
    "QA-appetizeKey": "90dycv9gb098u6xytcb6jnkvw8",
    "Production-appetizeKey": "e0fwwmkey5q74bn6v2w67k57xc"
  },
  "builds": {
    "live": {
      "excludedPackages": []
    },
    "preview": {
      "excludedPackages": [
        "shoutem.firebase",
        "shoutem.notification-center",
        "shoutem.push-notifications",
        "shoutem.shoutem-notification-center",
        "shoutem.code-push"
      ]
    }
  },
  "dependencies": {
    "shoutem.about": "~2.0.3",
    "shoutem.analytics": "~2.0.4",
    "shoutem.application": "~2.0.8",
    "shoutem.auth": "~2.0.11",
    "shoutem.books": "~2.0.4",
    "shoutem.camera": "~2.0.3",
    "shoutem.cms": "~2.0.3",
    "shoutem.code-push": "~2.0.3",
    "shoutem.deals": "~2.0.7",
    "shoutem.events": "~2.0.6",
    "shoutem.favorites": "~2.0.3",
    "shoutem.flurry-analytics": "~2.0.6",
    "shoutem.google-analytics": "~2.0.4",
    "shoutem.i18n": "~2.0.2",
    "shoutem.ical-events": "~2.0.5",
    "shoutem.layouts": "~2.0.1",
    "shoutem.loyalty": "~2.0.8",
    "shoutem.menu": "~2.0.3",
    "shoutem.navigation": "~2.0.14",
    "shoutem.news": "~2.0.4",
    "shoutem.notification-center": "~2.0.5",
    "shoutem.page": "~2.0.6",
    "shoutem.people": "~2.0.2",
    "shoutem.persist": "~2.0.4",
    "shoutem.photos": "~2.0.2",
    "shoutem.places": "~2.0.4",
    "shoutem.platform-analytics": "~2.0.3",
    "shoutem.preview": "~2.0.1",
    "shoutem.products": "~2.0.2",
    "shoutem.push-notifications": "~2.0.3",
    "shoutem.redux": "~2.0.5",
    "shoutem.rss": "~2.0.3",
    "shoutem.rss-news": "~2.0.5",
    "shoutem.rss-photos": "~2.0.2",
    "shoutem.rss-videos": "~2.0.2",
    "shoutem.rubicon-theme": "~2.0.6",
    "shoutem.shopify": "~2.0.6",
    "shoutem.social": "~2.0.6",
    "shoutem.sub-navigation": "~2.0.1",
    "shoutem.theme": "~2.0.3",
    "shoutem.video": "~2.0.2",
    "shoutem.vimeo": "~2.0.2",
    "shoutem.web-view": "~2.0.9",
    "shoutem.wordpress": "~2.0.11",
    "shoutem.youtube": "~2.0.5"
  }
}
